MANIFEST.in
README.markdown
roar
setup.py
_hooks/deploy_rsync.py
_hooks/markdown2.py
_hooks/posts.py
_hooks/posts_ui.py
_hooks/status.py
_hooks/template_filters.py
roar.egg-info/PKG-INFO
roar.egg-info/SOURCES.txt
roar.egg-info/dependency_links.txt
roar.egg-info/top_level.txt