Metadata-Version: 1.0
Name: roar
Version: 0.1.2
Summary: Static website generator based on Growl
Home-page: http://github.com/Connectical/roar
Author: Adrian Perez
Author-email: aperez@connectical.com
License: UNKNOWN
Platform: UNKNOWN
Classifier: Environment :: Console
Classifier: Development Status :: 4 - Beta
Classifier: Intended Audience :: Developers
Classifier: Intended Audience :: End Users/Desktop
Classifier: License :: OSI Approved :: GNU General Public License (GPL)
Classifier: Natural Language :: English
Classifier: Operating System :: OS Independent
Classifier: Programming Language :: Python :: 2
Classifier: Topic :: Internet :: WWW/HTTP :: Site Management
